amapy_plugin_s3/__init__.py
amapy_plugin_s3/aws_auth.py
amapy_plugin_s3/aws_blob.py
amapy_plugin_s3/aws_http_handler.py
amapy_plugin_s3/aws_mount_handler.py
amapy_plugin_s3/aws_storage.py
amapy_plugin_s3/aws_storage_mixin.py
amapy_plugin_s3/bucket_cors.py
amapy_plugin_s3/s3_proxy.py
amapy_plugin_s3/signed_url.py
amapy_plugin_s3/mounted_bucket/__init__.py
amapy_plugin_s3/mounted_bucket/async_mount_copy.py
amapy_plugin_s3/mounted_bucket/async_mount_transporter.py
amapy_plugin_s3/mounted_bucket/mounted_resource.py
amapy_plugin_s3/mounted_bucket/mounted_url.py
amapy_plugin_s3/mounted_bucket/tests/__init__.py
amapy_plugin_s3/mounted_bucket/tests/test_mounted_url.py
amapy_plugin_s3/tests/__init__.py
amapy_plugin_s3/tests/test_aws_storage.py
amapy_plugin_s3/transporter/__init__.py
amapy_plugin_s3/transporter/aws_transport_resource.py
amapy_plugin_s3/transporter/async_aws/__init__.py
amapy_plugin_s3/transporter/async_aws/async_aws_transporter.py
amapy_plugin_s3/transporter/async_aws/async_copy.py
amapy_plugin_s3/transporter/async_aws/async_download.py
amapy_plugin_s3/transporter/async_aws/async_update_blob.py
amapy_plugin_s3/transporter/async_aws/async_upload.py
amapy_plugin_s3/transporter/async_aws/tests/__init__.py
amapy_plugin_s3/transporter/async_aws/tests/test_async_aws_transporter.py
amapy_plugin_s3/transporter/legacy_aws/__init__.py
amapy_plugin_s3/transporter/legacy_aws/async_download.py
amapy_plugin_s3/transporter/legacy_aws/async_upload.py
amapy_plugin_s3/transporter/legacy_aws/legacy_aws_transporter.py
amapy_plugin_s3/transporter/legacy_aws/tests/__init__.py
amapy_plugin_s3/transporter/legacy_aws/tests/test_legacy_aws_transporter.py
amapy_plugin_s3-1.0.1.dist-info/METADATA
amapy_plugin_s3-1.0.1.dist-info/WHEEL
amapy_plugin_s3-1.0.1.dist-info/top_level.txt
amapy_plugin_s3-1.0.1.dist-info/RECORD
